Workbook

Sheet Sheet1
A1: logo | B1: ticker | E1: API | F1: company_name | G1: latest_price | H1: market_cap | I1: pe_ttm | J1: ps_ttm | K1: ipo_date | L1: ipo_fund | M1: revenue_2024 | N1: profit_2024 | O1: company_intro | Q1: funding_2020 | R1: funding_2021 | S1: funding_2022 | T1: funding_2023 | U1: funding_2024 | W1: logo
B2: 证券代码 | D2: ="https://img.logo.dev/ticker/"&C2&"?token="&$E$2&"&format=png&size=1024" -> https://img.logo.dev/ticker/?token=pk_FJ9NGdqpQP-_T1hBQT4O5A&format=png&size=1024 | E2: pk_FJ9NGdqpQP-_T1hBQT4O5A | F2: 证券简称 | G2: 最新收盘价 | H2: 总市值1 [交易日期] 最新收盘日 [币种] 美元 [单位] 亿元 | I2: 市盈率PE(TTM) [交易日期] 最新收盘日 [单位] 倍 | J2: 市销率PS(TTM) [交易日期] 最新收盘日 | K2: 上市日期 | L2: 首发募集资金 [币种] 原始币种 [单位] 亿元 | M2: 营业收入 [报告期] 2025年报 [报表类型] 合并报表 [币种] 美元 [单位] 亿元 | N2: 净利润 [报告期] 2025年报 [报表类型] 合并报表 [币种] 美元 [单位] 亿元 | O2: 公司简介 | P2: 发行方式 | Q2: 筹资活动产生的现金流量净额 [报告期] 2020年报 [报表类型] 合并报表 [币种] 美元 [单位] 亿元 | R2: 筹资活动产生的现金流量净额 [报告期] 2021年报 [报表类型] 合并报表 [币种] 美元 [单位] 亿元 | S2: 筹资活动产生的现金流量净额 [报告期] 2022年报 [报表类型] 合并报表 [币种] 美元 [单位] 亿元 | T2: 筹资活动产生的现金流量净额 [报告期] 2023年报 [报表类型] 合并报表 [币种] 美元 [单位] 亿元 | U2: 筹资活动产生的现金流量净额 [报告期] 2024年报 [报表类型] 合并报表 [币种] 美元 [单位] 亿元 | V2: 是否SPAC上市
A3: =_xlfn.IMAGE(D3,"",3,160,160) -> #NAME? | B3: 9690.HK | C3: =UPPER(LEFT(B3,FIND(".",B3&".")-1)) -> 9690 | D3: ="https://img.logo.dev/ticker/"&C3&"?token="&$E$2&"&format=png&size=1024" -> https://img.logo.dev/ticker/9690?token=pk_FJ9NGdqpQP-_T1hBQT4O5A&format=png&size=1024 | F3: 途虎-W | G3: 328.26 | H3: 718.38279 | I3: 51.057766 | J3: 3.5350004 | K3: 42853 | L3: 2.25 | M3: 203.22 | N3: 14.07 | O3: Carvana Co.是一家领先的电子商务平台，专注于买卖二手车。它通过提供广泛的选择、优惠的价格、优质的产品、透明的定价以及简单、无压力的交易体验来改变二手车的买卖方式。 | P3: 公开发售 | Q3: 11.6499 | R3: 35.28 | S3: 38.99 | T3: -8.68 | U3: 2.61 | V3: 0
A4: =_xlfn.IMAGE(D4,"",3,160,160) -> #NAME? | B4: 3669.HK | C4: =UPPER(LEFT(B4,FIND(".",B4&".")-1)) -> 3669 | D4: ="https://img.logo.dev/ticker/"&C4&"?token="&$E$2&"&format=png&size=1024" -> https://img.logo.dev/ticker/3669?token=pk_FJ9NGdqpQP-_T1hBQT4O5A&format=png&size=1024 | F4: 永达汽车 | G4: 193.58 | H4: 67.192659 | I4: 10.351665 | J4: 0.24317501 | K4: 29707 | L4: 0.08 | M4: 276.314 | N4: 6.491 | O4: 全美汽车租赁公司是一家美国最大的汽车零售商。截至2023年12月31日，全美汽车租赁公司拥有并经营着位于美国252个门店的349个新车特许经营权，主要位于太阳带地区的大都会市场。其门店销售34种不同的新车品牌。全美汽车租赁公司销售的新车核心品牌，占2023年全美汽车租赁公司销售的新车总数的约88%，是由丰田（包括雷克萨斯）、本田、福特、通用汽车、宝马、梅赛德斯-奔驰、斯泰兰蒂斯和大众（包括奥迪和保时捷）制造的。 | P4: 公开发售 | Q4: -6.067 | R4: -16.765 | S4: -11.54 | T4: -1.725 | U4: -3.006 | V4: 0
A5: =_xlfn.IMAGE(D5,"",3,160,160) -> #NAME? | B5: 2473.HK | C5: =UPPER(LEFT(B5,FIND(".",B5&".")-1)) -> 2473 | D5: ="https://img.logo.dev/ticker/"&C5&"?token="&$E$2&"&format=png&size=1024" -> https://img.logo.dev/ticker/2473?token=pk_FJ9NGdqpQP-_T1hBQT4O5A&format=png&size=1024 | F5: 喜相逢集团 | G5: 115.91 | H5: 100.28707 | I5: 28.195492 | J5: 2.1248779 | K5: 43095 | L5: 20.42 | M5: 46.182317 | N5: 3.4907591 | O5: 公司是国际领先的移动出行科技公司之一，致力于实现智慧出行的全球共享。公司深度聚焦于智能座舱、组合辅助驾驶和网联服务三大领域的高效融合，持续开发高度集成的智能硬件和领先的软件算法，为全球客户提供安全、愉悦和绿色的移动出行整体解决方案和服务。凭借39年来在设计、开发、生产过程中的深厚积淀，公司不断拓展自身在研发创新、客户服务、安全验证方面的综合实力，构筑从智慧出行到智慧交通的技术链路，积极应对汽车行业在新四化趋势下的挑战，满足汽车厂商对不同产品组合及业务开发模式的多元需求。为驾乘者提供卓越的出行体验的同时，也给未来出行带来更多想象空间。公司积极响应全球碳中和战略，从经济、社会、环境三个维度出发，推动落实安全可靠、成长共赢、绿色环保三大可持续发展目标。在回馈社会的同时，尊重公司每一位员工，为雇员打造多元共生的工作环境和高能成长的发展平台。我们鼓励全球各分部之间平等开放、协同发展，公司人秉承同一使命，共赴一致目标——创领安全、愉悦和绿色的出行生活。 | Q5: -0.17411196 | R5: 0.72846175 | S5: 0.52665131 | T5: -0.3860932 | U5: -0.59438385
A6: =_xlfn.IMAGE(D6,"",3,160,160) -> #NAME? | B6: 300496.SZ | C6: =UPPER(LEFT(B6,FIND(".",B6&".")-1)) -> 300496 | D6: ="https://img.logo.dev/ticker/"&C6&"?token="&$E$2&"&format=png&size=1024" -> https://img.logo.dev/ticker/300496?token=pk_FJ9NGdqpQP-_T1hBQT4O5A&format=png&size=1024 | F6: 中科创达 | G6: 70.75 | H6: 47.258065 | I6: 67.280434 | J6: 4.7674136 | K6: 42348 | L6: 5.8175 | M6: 7.4572 | N6: 0.5668 | O6: 公司是全球领先的智能平台技术提供商。自2008年成立以来，公司致力于提供卓越的智能终端操作系统平台技术及解决方案，助力并加速智能手机、智能物联网、智能汽车等领域的产品化与技术创新。源于多年在Android、Linux、Windows和HTML5等操作系统技术的研发与创新，中科创达形成了从硬件驱动、操作系统内核、中间件到上层应用全面的技术体系。积累了丰富的研发经验和众多自有知识产权，具备强有力的技术开发和服务能力。核心技术涵盖了通信协议栈、深度学习、图形图像算法、操作系统优化和安全技术等多个方面。中科创达与智能终端产业链中的芯片、元器件、终端、软件与互联网厂商以及运营商等全球领先企业拥有紧密的合作关系，具有独特的垂直整合优势。 | Q6: 2.3453072 | R6: 0.541429 | S6: 3.6014762 | T6: -0.18507 | U6: -0.26345473
A7: =_xlfn.IMAGE(D7,"",3,160,160) -> #NAME? | B7: 002920.SZ | C7: =UPPER(LEFT(B7,FIND(".",B7&".")-1)) -> 002920 | D7: ="https://img.logo.dev/ticker/"&C7&"?token="&$E$2&"&format=png&size=1024" -> https://img.logo.dev/ticker/002920?token=pk_FJ9NGdqpQP-_T1hBQT4O5A&format=png&size=1024 | F7: 德赛西威 | G7: 13.84 | H7: 14.626677 | I7: 20.642992 | J7: 0.67267706 | K7: 45195 | L7: 13.150424 | M7: 38.2989 | N7: 2.789 | O7: 公司是中国领先的线上线下一体化汽车服务平台之一。截至2023年3月31日，公司的旗舰应用程序「途虎养车」和线上界面拥有100.2百万名注册用户。截至2023年3月31日止最近十二个月，公司拥有17.1百万名交易用户，较截至2022年3月31日止同期的15.5百万名增加9.9%。根据灼识咨询报告，截至2023年3月31日止三个月，公司的平均月活跃用户达到10.2百万名，公司的平台成为中国汽车服务供应商聚集的最大车主社区。公司的服务网络不断扩张，在全国拥有超过4,700家途虎工场店和超过19,000家合作门店，覆盖大部分地级市。公司有三种不同类型的门店，包括公司的自营途虎工场店、加盟途虎工场店和第三方合作门店。加盟途虎工场店采用与自营途虎工场店相同的标准及我们的专有技术系统运营。公司在中国各地亦有大量的合作门店，其主要向通过线上界面下达订单的客户提供安装服务，作为途虎工场店的补充。根据灼识咨询报告，就所运营汽车服务门店数目及品牌认知度而言，途虎为中国领先的独立汽车服务品牌。平台服务在中国销售的大多数乘用车车型，满足从轮胎和底盘零部件更换到汽车保养、维修、汽车美容等汽车服务需求。 | P7: 发售以供认购,发售以供配售 | Q7: -1.5955739 | R7: 2.2082861 | S7: 1.3439063 | T7: 1.9057492 | U7: -0.33521785 | V7: 0
A8: =_xlfn.IMAGE(D8,"",3,160,160) -> #NAME? | B8: CVNA.N | C8: =UPPER(LEFT(B8,FIND(".",B8&".")-1)) -> CVNA | D8: ="https://img.logo.dev/ticker/"&C8&"?token="&$E$2&"&format=png&size=1024" -> https://img.logo.dev/ticker/CVNA?token=pk_FJ9NGdqpQP-_T1hBQT4O5A&format=png&size=1024 | F8: CARVANA | G8: 1.47 | H8: 3.4862014 | I8: -0.76699078 | J8: 0.041822722 | K8: 41102 | L8: 13.201452 | M8: 136.73 | N8: 2.1 | O8: 中国永达汽车服务控股有限公司是一家主要从事汽车销售，提供售后服务、提供汽车经营租赁服务，以及分销汽车保险产品和汽车金融产品的公司。该公司通过两个分部开展业务。乘用车销售及服务分部从事乘用车销售、提供售后服务，主要包括维修及保养服务、若干乘用车销售相关配套服务及提供乘用车相关其他服务。汽车经营租赁服务分部从事汽车经营性出租。该公司主要在国内市场经营其业务。 | P8: 发售以供认购,发售以供配售,发售现有证券 | Q8: -4.8908167 | R8: -8.7240178 | S8: -4.0803277 | T8: -1.8051816 | U8: -2.7894566 | V8: 0
A9: =_xlfn.IMAGE(D9,"",3,160,160) -> #NAME? | B9: AN.N | C9: =UPPER(LEFT(B9,FIND(".",B9&".")-1)) -> AN | D9: ="https://img.logo.dev/ticker/"&C9&"?token="&$E$2&"&format=png&size=1024" -> https://img.logo.dev/ticker/AN?token=pk_FJ9NGdqpQP-_T1hBQT4O5A&format=png&size=1024 | F9: 全美汽车租赁 | G9: 1.19 | H9: 2.3535059 | I9: 39.248566 | J9: 1.0661232 | K9: 45239 | L9: 1.134375 | M9: 267.654 | N9: 6.922 | O9: 喜相逢集团控股有限公司是一家主要提供汽车服务，包括汽车零售、汽车融资、汽车租赁及汽车相关服务的公司。该公司主营三项业务。喜相逢集团控股有限公司是一家主要提供汽车服务，包括汽车零售、汽车融资、汽车租赁及汽车相关服务的公司。融资租赁收入业务主要向个人客户提供汽车融资租赁服务。汽车租赁业务向个人及企业客户提供汽车经营租赁服务。其他汽车相关业务爲汽车用户营运汽车售后服务平台，以促成第三方供应商于汽车使用生命周期内向汽车用家提供售后使用解决方案。该公司产品销往国内市场。 | P9: 发售以供认购,发售以供配售 | Q9: -0.24982605 | R9: 0.31851091 | S9: 0.45203888 | T9: 0.32268344 | U9: 0.5488704 | V9: 0

Sheet Sheet2
A1: 证券代码 | B1: 证券简称 | C1: 最新市值（亿） | D1: PE TTM | E1: Ps TTM | F1: Pe平均值 | G1: pe平均值
A2: =Sheet1!B3 -> 9690.HK | B2: =Sheet1!F3 -> 途虎-W | C2: =Sheet1!H3 -> 718.38279 | D2: =Sheet1!I3 -> 51.057766 | E2: =Sheet1!J3 -> 3.5350004 | F2: =G2 -> 30.858561 | G2: =AVERAGE(D2:D8) -> 30.858561
A3: =Sheet1!B4 -> 3669.HK | B3: =Sheet1!F4 -> 永达汽车 | C3: =Sheet1!H4 -> 67.192659 | D3: =Sheet1!I4 -> 10.351665 | E3: =Sheet1!J4 -> 0.24317501 | F3: =G2 -> 30.858561
A4: =Sheet1!B5 -> 2473.HK | B4: =Sheet1!F5 -> 喜相逢集团 | C4: =Sheet1!H5 -> 100.28707 | D4: =Sheet1!I5 -> 28.195492 | E4: =Sheet1!J5 -> 2.1248779 | F4: =G2 -> 30.858561
A5: =Sheet1!B6 -> 300496.SZ | B5: =Sheet1!F6 -> 中科创达 | C5: =Sheet1!H6 -> 47.258065 | D5: =Sheet1!I6 -> 67.280434 | E5: =Sheet1!J6 -> 4.7674136 | F5: =G2 -> 30.858561
A6: =Sheet1!B7 -> 002920.SZ | B6: =Sheet1!F7 -> 德赛西威 | C6: =Sheet1!H7 -> 14.626677 | D6: =Sheet1!I7 -> 20.642992 | E6: =Sheet1!J7 -> 0.67267706 | F6: =G2 -> 30.858561
A7: =Sheet1!B8 -> CVNA.N | B7: =Sheet1!F8 -> CARVANA | C7: =Sheet1!H8 -> 3.4862014 | D7: =Sheet1!I8 -> -0.76699078 | E7: =Sheet1!J8 -> 0.041822722 | F7: =G2 -> 30.858561
A8: =Sheet1!B9 -> AN.N | B8: =Sheet1!F9 -> 全美汽车租赁 | C8: =Sheet1!H9 -> 2.3535059 | D8: =Sheet1!I9 -> 39.248566 | E8: =Sheet1!J9 -> 1.0661232 | F8: =G2 -> 30.858561
